[
  {
    "ContainingType": "CRMF360.Api.Controllers.AuthController",
    "Method": "Login",
    "RelativePath": "api/Auth/login",
    "HttpMethod": "POST",
    "IsController": true,
    "Order": 0,
    "Parameters": [
      {
        "Name": "request",
        "Type": "CRMF360.Api.Controllers.AuthController\u002BLoginRequest",
        "IsRequired": true
      }
    ],
    "ReturnTypes": [
      {
        "Type": "CRMF360.Api.Controllers.AuthController\u002BLoginResponse",
        "MediaTypes": [
          "text/plain",
          "application/json",
          "text/json"
        ],
        "StatusCode": 200
      },
      {
        "Type": "Microsoft.AspNetCore.Mvc.ProblemDetails",
        "MediaTypes": [
          "text/plain",
          "application/json",
          "text/json"
        ],
        "StatusCode": 401
      }
    ]
  },
  {
    "ContainingType": "CRMF360.Api.Controllers.RolesController",
    "Method": "GetAll",
    "RelativePath": "api/Roles",
    "HttpMethod": "GET",
    "IsController": true,
    "Order": 0,
    "Parameters": [],
    "ReturnTypes": [
      {
        "Type": "System.Collections.Generic.List\u00601[[CRMF360.Application.Roles.RoleDto, CRMF360.Application, Version=1.0.0.0, Culture=neutral, PublicKeyToken=null]]",
        "MediaTypes": [
          "text/plain",
          "application/json",
          "text/json"
        ],
        "StatusCode": 200
      }
    ]
  },
  {
    "ContainingType": "CRMF360.Api.Controllers.RolesController",
    "Method": "Create",
    "RelativePath": "api/Roles",
    "HttpMethod": "POST",
    "IsController": true,
    "Order": 0,
    "Parameters": [
      {
        "Name": "dto",
        "Type": "CRMF360.Application.Roles.CreateRoleDto",
        "IsRequired": true
      }
    ],
    "ReturnTypes": [
      {
        "Type": "CRMF360.Application.Roles.RoleDto",
        "MediaTypes": [
          "text/plain",
          "application/json",
          "text/json"
        ],
        "StatusCode": 200
      }
    ]
  },
  {
    "ContainingType": "CRMF360.Api.Controllers.RolesController",
    "Method": "GetById",
    "RelativePath": "api/Roles/{id}",
    "HttpMethod": "GET",
    "IsController": true,
    "Order": 0,
    "Parameters": [
      {
        "Name": "id",
        "Type": "System.Int32",
        "IsRequired": true
      }
    ],
    "ReturnTypes": [
      {
        "Type": "CRMF360.Application.Roles.RoleDto",
        "MediaTypes": [
          "text/plain",
          "application/json",
          "text/json"
        ],
        "StatusCode": 200
      }
    ]
  },
  {
    "ContainingType": "CRMF360.Api.Controllers.RolesController",
    "Method": "Update",
    "RelativePath": "api/Roles/{id}",
    "HttpMethod": "PUT",
    "IsController": true,
    "Order": 0,
    "Parameters": [
      {
        "Name": "id",
        "Type": "System.Int32",
        "IsRequired": true
      },
      {
        "Name": "dto",
        "Type": "CRMF360.Application.Roles.UpdateRoleDto",
        "IsRequired": true
      }
    ],
    "ReturnTypes": []
  },
  {
    "ContainingType": "CRMF360.Api.Controllers.RolesController",
    "Method": "Delete",
    "RelativePath": "api/Roles/{id}",
    "HttpMethod": "DELETE",
    "IsController": true,
    "Order": 0,
    "Parameters": [
      {
        "Name": "id",
        "Type": "System.Int32",
        "IsRequired": true
      }
    ],
    "ReturnTypes": []
  },
  {
    "ContainingType": "CRMF360.Api.Controllers.UsersController",
    "Method": "Create",
    "RelativePath": "api/Users",
    "HttpMethod": "POST",
    "IsController": true,
    "Order": 0,
    "Parameters": [
      {
        "Name": "dto",
        "Type": "CRMF360.Application.Users.CreateUserDto",
        "IsRequired": true
      }
    ],
    "ReturnTypes": [
      {
        "Type": "CRMF360.Application.Users.UserDto",
        "MediaTypes": [
          "text/plain",
          "application/json",
          "text/json"
        ],
        "StatusCode": 200
      }
    ]
  },
  {
    "ContainingType": "CRMF360.Api.Controllers.UsersController",
    "Method": "GetAll",
    "RelativePath": "api/Users",
    "HttpMethod": "GET",
    "IsController": true,
    "Order": 0,
    "Parameters": [],
    "ReturnTypes": [
      {
        "Type": "System.Collections.Generic.IEnumerable\u00601[[CRMF360.Application.Users.UserDto, CRMF360.Application, Version=1.0.0.0, Culture=neutral, PublicKeyToken=null]]",
        "MediaTypes": [
          "text/plain",
          "application/json",
          "text/json"
        ],
        "StatusCode": 200
      }
    ]
  },
  {
    "ContainingType": "CRMF360.Api.Controllers.UsersController",
    "Method": "GetById",
    "RelativePath": "api/Users/{id}",
    "HttpMethod": "GET",
    "IsController": true,
    "Order": 0,
    "Parameters": [
      {
        "Name": "id",
        "Type": "System.Int32",
        "IsRequired": true
      }
    ],
    "ReturnTypes": [
      {
        "Type": "CRMF360.Application.Users.UserDto",
        "MediaTypes": [
          "text/plain",
          "application/json",
          "text/json"
        ],
        "StatusCode": 200
      }
    ]
  },
  {
    "ContainingType": "CRMF360.Api.Controllers.UsersController",
    "Method": "Update",
    "RelativePath": "api/Users/{id}",
    "HttpMethod": "PUT",
    "IsController": true,
    "Order": 0,
    "Parameters": [
      {
        "Name": "id",
        "Type": "System.Int32",
        "IsRequired": true
      },
      {
        "Name": "dto",
        "Type": "CRMF360.Application.Users.UpdateUserDto",
        "IsRequired": true
      }
    ],
    "ReturnTypes": [
      {
        "Type": "CRMF360.Application.Users.UserDto",
        "MediaTypes": [
          "text/plain",
          "application/json",
          "text/json"
        ],
        "StatusCode": 200
      }
    ]
  },
  {
    "ContainingType": "CRMF360.Api.Controllers.UsersController",
    "Method": "Delete",
    "RelativePath": "api/Users/{id}",
    "HttpMethod": "DELETE",
    "IsController": true,
    "Order": 0,
    "Parameters": [
      {
        "Name": "id",
        "Type": "System.Int32",
        "IsRequired": true
      }
    ],
    "ReturnTypes": []
  }
]